hkavr/__init__.py
hkavr/hkavr.py
hkavr-0.0.5.dist-info/LICENSE
hkavr-0.0.5.dist-info/METADATA
hkavr-0.0.5.dist-info/WHEEL
hkavr-0.0.5.dist-info/top_level.txt
hkavr-0.0.5.dist-info/RECORD
